pyOptional/__init__.py
pyOptional/exceptions.py
pyOptional/optional.py
pyOptional/tests/__init__.py
pyOptional/tests/test_optional.py
pyOptional-1.1.2.dist-info/DESCRIPTION.rst
pyOptional-1.1.2.dist-info/METADATA
pyOptional-1.1.2.dist-info/RECORD
pyOptional-1.1.2.dist-info/WHEEL
pyOptional-1.1.2.dist-info/metadata.json
pyOptional-1.1.2.dist-info/top_level.txt
