Metadata-Version: 2.0
Name: pyOptional
Version: 1.1.2
Summary: Library provided implementation Optional object similar to Java optional. Using this object, You will never check "if x is None"
Home-page: https://github.com/PawelJ-PL/pyOptional
Author: Pawel
Author-email: inne.poczta@gmail.com
License: MIT
Keywords: Python optional
Platform: UNKNOWN
Classifier: Development Status :: 5 - Production/Stable
Classifier: Intended Audience :: Developers
Classifier: License :: OSI Approved :: MIT License
Classifier: Programming Language :: Python :: 3 :: Only
Classifier: Topic :: Software Development :: Libraries
Requires-Python: >=3
Provides-Extra: test
Requires-Dist: coverage; extra == 'test'
